[
    {"id": "1","name": "Код, который умещается в голове", "description": "233ed598-37a5-4c67-b76e-d270904293dd", "created": 1707494116622, "status":  false},
    {"id": "2","name": "Фундаментальный подход к программной архитектуре", "description": "5d10c9a1-d358-440b-8ca2-acd886e83e9c", "created": 1705898113622, "status":  false},
    {"id": "3","name": "Фундаментальный подход к программной архитектуре", "description": "72b26b73-7255-4418-9ad6-0f032c5c84da", "created": 1607898115622, "status":  false},
    {"id": "4","name": "Фундаментальный подход к программной архитектуре", "description": "5b2c8b3e-33b9-4ce4-a73a-ef70d76dad45", "created": 1707898112622, "status":  false}
]

